CaptchaGen/CaptchaGen.py
CaptchaGen/__init__.py
captchagen-0.1.0.dist-info/licenses/LICENSE
captchagen-0.1.0.dist-info/METADATA
captchagen-0.1.0.dist-info/WHEEL
captchagen-0.1.0.dist-info/top_level.txt
captchagen-0.1.0.dist-info/RECORD
