Metadata-Version: 2.4
Name: CaptchaGen
Version: 0.1.0
Summary: Configurable CAPTCHA generator in Python with rotation, noise, and color options.
Author-email: Farahbakhsh3 <farahbakhsh3@gmail.com>
License: GPL-3.0-or-later
Project-URL: Homepage, https://github.com/farahbakhsh3/captcha-generator
Project-URL: Documentation, https://github.com/farahbakhsh3/captcha-generator
Project-URL: Repository, https://github.com/farahbakhsh3/captcha-generator
Keywords: captcha,image,generator,python
Classifier: Programming Language :: Python :: 3
Classifier: Operating System :: OS Independent
Classifier: License :: OSI Approved :: GNU General Public License v3 or later (GPLv3+)
Requires-Python: >=3.9
License-File: LICENSE
Requires-Dist: Pillow>=10.0.0
Dynamic: license-file
